rbb/__init__.py
draw_rbb-0.2.0.dist-info/METADATA
draw_rbb-0.2.0.dist-info/WHEEL
draw_rbb-0.2.0.dist-info/top_level.txt
draw_rbb-0.2.0.dist-info/RECORD
