Metadata-Version: 2.1
Name: draw-rbb
Version: 0.2.0
Summary: Drawing rounded bounding box with text
Author: Alex Choi
Author-email: geol.choi@vivity.ai
License: MIT
Keywords: python,opencv,rounded bounding box
Classifier: Development Status :: 1 - Planning
Classifier: Intended Audience :: Developers
Classifier: Programming Language :: Python :: 3
Classifier: Operating System :: Unix
Classifier: Operating System :: MacOS :: MacOS X
Classifier: Operating System :: Microsoft :: Windows
Requires-Dist: opencv-python ==4.8.1.78
Requires-Dist: twine ==4.0.2
